{"global_regime": "CHOPSAW", "color": "red", "trending_coins": 0, "neutral_coins": 0, "chopsaw_coins": 7, "coins": {"ETH": {"regime": "CHOPSAW", "color": "red", "atr_percent": 0.2937594346095797, "adx": 5.485232067510347, "bb_width": 0.8677649402802924, "details": "ADX=5.5 (lemah), BB_Width=0.87% (sempit)"}, "XRP": {"regime": "CHOPSAW", "color": "red", "atr_percent": 0.2857660080686917, "adx": 30.158730158728154, "bb_width": 0.9126683543666803, "details": "ADX=30.2 (lemah), BB_Width=0.91% (sempit)"}, "SOL": {"regime": "CHOPSAW", "color": "red", "atr_percent": 0.3215557053139887, "adx": 6.498545101840958, "bb_width": 0.6706945238564209, "details": "ADX=6.5 (lemah), BB_Width=0.67% (sempit)"}, "SUI": {"regime": "CHOPSAW", "color": "red", "atr_percent": 0.4458489677704693, "adx": 12.946979038224848, "bb_width": 1.5107788438930578, "details": "ADX=12.9 (lemah), BB_Width=1.51% (sempit)"}, "BTC": {"regime": "CHOPSAW", "color": "red", "atr_percent": 0.24068322981366463, "adx": 9.651741293532346, "bb_width": 0.7999097246186653, "details": "ADX=9.7 (lemah), BB_Width=0.80% (sempit)"}, "BNB": {"regime": "CHOPSAW", "color": "red", "atr_percent": 0.18491069259712717, "adx": 22.58953168044097, "bb_width": 0.7127181374750937, "details": "ADX=22.6 (lemah), BB_Width=0.71% (sempit)"}, "VVV": {"regime": "CHOPSAW", "color": "red", "atr_percent": 0.8424750842475092, "adx": 9.728867623604163, "bb_width": 1.921050917041637, "details": "ADX=9.7 (lemah), BB_Width=1.92% (sempit)"}}}